eyconf/__init__.py
eyconf/asdict.py
eyconf/cli.py
eyconf/constants.py
eyconf/decorators.py
eyconf/generate_yaml.py
eyconf/py.typed
eyconf/type_utils.py
eyconf/utils.py
eyconf/config/__init__.py
eyconf/config/base.py
eyconf/config/extra_fields.py
eyconf/config/file.py
eyconf/validation/__init__.py
eyconf/validation/_to_json.py
eyconf-0.6.1.dist-info/METADATA
eyconf-0.6.1.dist-info/WHEEL
eyconf-0.6.1.dist-info/licenses/LICENSE
eyconf-0.6.1.dist-info/RECORD
