Metadata-Version: 2.4
Name: eyconf
Version: 0.6.1
Summary: Easy Yaml based Configuration for Python
Author-email: "Sebastian B. Mohr" <sebastian@mohrenclan.de>, "F. Paul Spitzner" <github@makeitso.one>
License-File: LICENSE
Classifier: Development Status :: 3 - Alpha
Classifier: Intended Audience :: Science/Research
Classifier: License :: OSI Approved :: GNU General Public License v3 (GPLv3)
Classifier: Operating System :: OS Independent
Classifier: Programming Language :: Python :: 3
Classifier: Programming Language :: Python :: 3.10
Classifier: Programming Language :: Python :: 3.11
Classifier: Programming Language :: Python :: 3.12
Classifier: Programming Language :: Python :: 3.13
Requires-Python: >=3.10
Requires-Dist: jsonschema
Requires-Dist: pyyaml
Requires-Dist: typing-extensions
Provides-Extra: cli
Requires-Dist: typer; extra == 'cli'
Provides-Extra: dev
Requires-Dist: pre-commit; extra == 'dev'
Requires-Dist: pytest; extra == 'dev'
Requires-Dist: pytest-cov>=5.0.0; extra == 'dev'
Requires-Dist: ruff>=0.8.6; extra == 'dev'
Requires-Dist: typer; extra == 'dev'
Provides-Extra: docs
Requires-Dist: furo>=2024.8.6; extra == 'docs'
Requires-Dist: myst-nb>=1.1.2; extra == 'docs'
Requires-Dist: myst-parser>=4.0.0; extra == 'docs'
Requires-Dist: sphinx-copybutton>=0.5.2; extra == 'docs'
Requires-Dist: sphinx-design>=0.6.1; extra == 'docs'
Requires-Dist: sphinx-inline-tabs>=2023.4.21; extra == 'docs'
Requires-Dist: sphinx>=8.0.2; extra == 'docs'
Requires-Dist: sphinxcontrib-typer[html]>=0.5.0; extra == 'docs'
Provides-Extra: test
Requires-Dist: pytest; extra == 'test'
Requires-Dist: pytest-cov>=5.0.0; extra == 'test'
Provides-Extra: typed
Requires-Dist: mypy; extra == 'typed'
Requires-Dist: types-jsonschema; extra == 'typed'
Requires-Dist: types-pyyaml; extra == 'typed'
